CMakeLists.txt
LICENSE
MANIFEST.in
NOTICE
README.md
pyproject.toml
setup.py
vcpkg.json
cpp/cmake/modules/FindBrotli.cmake
cpp/cmake/modules/FindCSP.cmake
cpp/cmake/modules/FindColor.cmake
cpp/cmake/modules/FindDepsBase.cmake
cpp/cmake/modules/FindDepsKafkaAdapter.cmake
cpp/cmake/modules/FindDepsParquetAdapter.cmake
cpp/cmake/modules/FindGRPC.cmake
cpp/cmake/modules/FindNumpy.cmake
cpp/cmake/modules/FindPyArrow.cmake
cpp/cmake/modules/FindPythonHeaders.cmake
cpp/cmake/modules/FindRdKafka.cmake
cpp/cmake/modules/Findcsp_autogen.cmake
cpp/cmake/modules/Findlz4.cmake
cpp/cmake/modules/Findutf8proc.cmake
cpp/csp/adapters/CMakeLists.txt
cpp/csp/adapters/kafka/CMakeLists.txt
cpp/csp/adapters/kafka/KafkaAdapterManager.cpp
cpp/csp/adapters/kafka/KafkaAdapterManager.h
cpp/csp/adapters/kafka/KafkaConsumer.cpp
cpp/csp/adapters/kafka/KafkaConsumer.h
cpp/csp/adapters/kafka/KafkaInputAdapter.cpp
cpp/csp/adapters/kafka/KafkaInputAdapter.h
cpp/csp/adapters/kafka/KafkaOutputAdapter.cpp
cpp/csp/adapters/kafka/KafkaOutputAdapter.h
cpp/csp/adapters/kafka/KafkaPublisher.cpp
cpp/csp/adapters/kafka/KafkaPublisher.h
cpp/csp/adapters/kafka/KafkaSubscriber.cpp
cpp/csp/adapters/kafka/KafkaSubscriber.h
cpp/csp/adapters/parquet/ArrowIPCFileReaderWrapper.cpp
cpp/csp/adapters/parquet/ArrowIPCFileReaderWrapper.h
cpp/csp/adapters/parquet/ArrowIPCFileWriterWrapper.cpp
cpp/csp/adapters/parquet/ArrowIPCFileWriterWrapper.h
cpp/csp/adapters/parquet/ArrowSingleColumnArrayBuilder.h
cpp/csp/adapters/parquet/CMakeLists.txt
cpp/csp/adapters/parquet/DialectGenericListReaderInterface.h
cpp/csp/adapters/parquet/DialectGenericListWriterInterface.h
cpp/csp/adapters/parquet/FileReaderWrapper.cpp
cpp/csp/adapters/parquet/FileReaderWrapper.h
cpp/csp/adapters/parquet/FileWriterWrapper.cpp
cpp/csp/adapters/parquet/FileWriterWrapper.h
cpp/csp/adapters/parquet/FileWriterWrapperContainer.cpp
cpp/csp/adapters/parquet/FileWriterWrapperContainer.h
cpp/csp/adapters/parquet/ParquetDictBasketOutputWriter.cpp
csp_next.egg-info/PKG-INFO
csp_next.egg-info/SOURCES.txt
csp_next.egg-info/dependency_links.txt
csp_next.egg-info/requires.txt
csp_next.egg-info/top_level.txt