Metadata-Version: 2.1
Name: csp-next
Version: 0.0.2
Summary: csp is a high performance reactive stream processing library, written in C++ and Python
Author-email: the csp authors <CSPOpenSource@point72.com>
License:                                  Apache License
Project-URL: Repository, https://github.com/point72/csp
Project-URL: Homepage, https://github.com/Point72/csp
Project-URL: Documentation, https://github.com/Point72/csp/wiki
Project-URL: Tracker, https://github.com/point72/csp/issues
Classifier: Development Status :: 4 - Beta
Classifier: Programming Language :: Python :: Implementation :: CPython
Classifier: Programming Language :: Python :: Implementation :: PyPy
Classifier: Programming Language :: Python :: 3
Classifier: Programming Language :: Python :: 3.8
Classifier: Programming Language :: Python :: 3.9
Classifier: Programming Language :: Python :: 3.10
Classifier: Programming Language :: Python :: 3.11
Requires-Python: >=3.8
License-File: LICENSE
License-File: NOTICE
Requires-Dist: backports.zoneinfo; python_version < "3.9"
Requires-Dist: numpy
Requires-Dist: packaging
Requires-Dist: pandas
Requires-Dist: psutil
Requires-Dist: pyarrow>=7.0.0
Requires-Dist: pytz
Requires-Dist: ruamel.yaml
Requires-Dist: sqlalchemy
Provides-Extra: develop
Requires-Dist: bump2version>=1.0.0; extra == "develop"
Requires-Dist: build; extra == "develop"
Requires-Dist: graphviz; extra == "develop"
Requires-Dist: httpx<1,>=0.20; extra == "develop"
Requires-Dist: isort<6,>=5; extra == "develop"
Requires-Dist: ruamel.yaml; extra == "develop"
Requires-Dist: ruff<0.4,>=0.3; extra == "develop"
Requires-Dist: scikit-build; extra == "develop"
Requires-Dist: twine; extra == "develop"
Requires-Dist: wheel; extra == "develop"
Requires-Dist: polars; extra == "develop"
Requires-Dist: psutil; extra == "develop"
Requires-Dist: pytest; extra == "develop"
Requires-Dist: pytest-asyncio; extra == "develop"
Requires-Dist: pytest-cov; extra == "develop"
Requires-Dist: pytest-sugar; extra == "develop"
Requires-Dist: sqlalchemy; extra == "develop"
Requires-Dist: threadpoolctl; extra == "develop"
Requires-Dist: tornado; extra == "develop"
Requires-Dist: requests; extra == "develop"
Requires-Dist: slack-sdk>=3; extra == "develop"
Provides-Extra: symphony
Requires-Dist: requests; extra == "symphony"
Provides-Extra: slack
Requires-Dist: slack-sdk>=3; extra == "slack"
